dataprov/__init__.py
dataprov/dataprov.py
dataprov/dataprov_prov_schema.json
dataprov/cli/__init__.py
dataprov/cli/addattribution.py
dataprov/cli/newprovchain.py
dataprov/cli/report.py
dataprov/cli/visualize.py
dataprov-3.0.2.dist-info/licenses/LICENSE
dataprov-3.0.2.dist-info/METADATA
dataprov-3.0.2.dist-info/WHEEL
dataprov-3.0.2.dist-info/entry_points.txt
dataprov-3.0.2.dist-info/top_level.txt
dataprov-3.0.2.dist-info/RECORD
