Metadata-Version: 2.4
Name: dataprov
Version: 3.0.2
Summary: W3C PROV-compliant data provenance tracking library for recording processing chains
Author: Fredrik Warg
License: MIT License
Keywords: provenance,data-lineage,data-tracking,metadata,prov,w3c,prov-json
Classifier: Development Status :: 4 - Beta
Classifier: Intended Audience :: Developers
Classifier: Intended Audience :: Science/Research
Classifier: License :: OSI Approved :: MIT License
Classifier: Programming Language :: Python :: 3
Classifier: Programming Language :: Python :: 3.10
Classifier: Programming Language :: Python :: 3.11
Classifier: Programming Language :: Python :: 3.12
Classifier: Topic :: Software Development :: Libraries :: Python Modules
Classifier: Topic :: System :: Logging
Requires-Python: >=3.10
License-File: LICENSE
Provides-Extra: dev
Requires-Dist: pytest>=7.0; extra == "dev"
Requires-Dist: pytest-cov>=4.0; extra == "dev"
Requires-Dist: ruff>=0.8.0; extra == "dev"
Requires-Dist: pre-commit>=4.0; extra == "dev"
Dynamic: license-file
